trunk_sim/__init__.py
trunk_sim/data.py
trunk_sim/generate_trunk_model.py
trunk_sim/policy.py
trunk_sim/rollout.py
trunk_sim/simulator.py
trunk_sim/visualization.py
trunk_sim-0.2.1.dist-info/METADATA
trunk_sim-0.2.1.dist-info/WHEEL
trunk_sim-0.2.1.dist-info/licenses/LICENSE
trunk_sim-0.2.1.dist-info/RECORD
