Metadata-Version: 2.4
Name: trunk-sim
Version: 0.2.1
Summary: ASL Trunk simulator
License-File: LICENSE
Keywords: robotics,simulator,trunk
Requires-Python: >=3.12
Requires-Dist: matplotlib>=3.10.0
Requires-Dist: mediapy>=1.2.2
Requires-Dist: mujoco>=3.2.7
Requires-Dist: numpy>=2.2.3
Requires-Dist: pandas>=2.2.3
Requires-Dist: torch>=2.6.0
Requires-Dist: tqdm>=4.67.1
